LICENSE.txt
MANIFEST.in
NOTICE
README.md
setup.cfg
setup.py
spotrix/__init__.py
spotrix/app.py
spotrix/cli.py
spotrix/config.py
spotrix/constants.py
spotrix/dataframe.py
spotrix/errors.py
spotrix/exceptions.py
spotrix/extensions.py
spotrix/forms.py
spotrix/jinja_context.py
spotrix/legacy.py
spotrix/result_set.py
spotrix/schemas.py
spotrix/sql_lab.py
spotrix/sql_parse.py
spotrix/stats_logger.py
spotrix/viz.py
spotrix/x_typing.py
spotrix-frontend/package.json
spotrix.egg-info/PKG-INFO
spotrix.egg-info/SOURCES.txt
spotrix.egg-info/dependency_links.txt
spotrix.egg-info/entry_points.txt
spotrix.egg-info/not-zip-safe
spotrix.egg-info/requires.txt
spotrix.egg-info/top_level.txt
spotrix/annotation_layers/__init__.py
spotrix/annotation_layers/api.py
spotrix/annotation_layers/dao.py
spotrix/annotation_layers/filters.py
spotrix/annotation_layers/schemas.py
spotrix/annotation_layers/annotations/__init__.py
spotrix/annotation_layers/annotations/api.py
spotrix/annotation_layers/annotations/dao.py
spotrix/annotation_layers/annotations/filters.py
spotrix/annotation_layers/annotations/schemas.py
spotrix/annotation_layers/annotations/commands/__init__.py
spotrix/annotation_layers/annotations/commands/bulk_delete.py
spotrix/annotation_layers/annotations/commands/create.py
spotrix/annotation_layers/annotations/commands/delete.py
spotrix/annotation_layers/annotations/commands/exceptions.py
spotrix/annotation_layers/annotations/commands/update.py
spotrix/annotation_layers/commands/__init__.py
spotrix/annotation_layers/commands/bulk_delete.py
spotrix/annotation_layers/commands/create.py
spotrix/annotation_layers/commands/delete.py
spotrix/annotation_layers/commands/exceptions.py
spotrix/annotation_layers/commands/update.py
spotrix/async_events/__init__.py
spotrix/async_events/api.py
spotrix/cachekeys/__init__.py
spotrix/cachekeys/api.py
spotrix/cachekeys/schemas.py
spotrix/charts/__init__.py
spotrix/charts/api.py
spotrix/charts/dao.py
spotrix/charts/filters.py
spotrix/charts/post_processing.py
spotrix/charts/schemas.py
spotrix/charts/commands/__init__.py
spotrix/charts/commands/bulk_delete.py
spotrix/charts/commands/create.py
spotrix/charts/commands/data.py
spotrix/charts/commands/delete.py
