Metadata-Version: 2.1
Name: spotrix
Version: 1.2.0
Summary: A modern, enterprise-ready business intelligence web application
Home-page: https://github.com/Spotrix/spotrix
Download-URL: https://github.com/Spotrix/spotrix
Author: ciusji
Author-email: bqjimaster@gmail.com
License: Apache License, Version 2.0
Classifier: Programming Language :: Python :: 3.7
Classifier: Programming Language :: Python :: 3.8
Classifier: Programming Language :: Python :: 3.9
Classifier: Programming Language :: Python :: 3.10
Requires-Python: ~=3.7
Provides-Extra: athena
Provides-Extra: bigquery
Provides-Extra: clickhouse
Provides-Extra: cockroachdb
Provides-Extra: cors
Provides-Extra: crate
Provides-Extra: databricks
Provides-Extra: db2
Provides-Extra: dremio
Provides-Extra: drill
Provides-Extra: druid
Provides-Extra: solr
Provides-Extra: elasticsearch
Provides-Extra: exasol
Provides-Extra: excel
Provides-Extra: firebird
Provides-Extra: gsheets
Provides-Extra: hana
Provides-Extra: hive
Provides-Extra: impala
Provides-Extra: kylin
Provides-Extra: mmsql
Provides-Extra: mysql
Provides-Extra: oracle
Provides-Extra: pinot
Provides-Extra: postgres
Provides-Extra: presto
Provides-Extra: trino
Provides-Extra: prophet
Provides-Extra: redshift
Provides-Extra: rockset
Provides-Extra: shillelagh
Provides-Extra: snowflake
Provides-Extra: teradata
Provides-Extra: thumbnails
Provides-Extra: vertica
Provides-Extra: netezza
License-File: LICENSE.txt
License-File: NOTICE
